{
  "roll_no": "24EG107B01",
  "records": [
    {
      "_id": "698ac43c564599db8835974e",
      "className": "EML (AIML-B)",
      "rollNo": "24EG107B01",
      "date": "2026-02-10",
      "facultyId": null,
      "facultyName": null,
      "name": "abhinav",
      "section": "B",
      "status": "absent",
      "subject": "EML101",
      "time": null,
      "timestamp": "2026-02-10T05:38:47.786000",
      "type": "live"
    },
    {
      "_id": "698ad3f0564599db88359812",
      "date": "2026-01-18",
      "subject": "Java Programming",
      "rollNo": "24EG107B01",
      "className": "Section-B",
      "facultyId": "F001",
      "facultyName": "Demo Teacher",
      "name": "abhinav",
      "section": "B",
      "status": "present",
      "time": "11:02:00",
      "timestamp": "2026-02-10T06:45:02.610000",
      "type": "dummy"
    },
    {
      "_id": "698ad3f0564599db88359813",
      "date": "2026-01-23",
      "subject": "Java Programming",
      "rollNo": "24EG107B01",
      "className": "Section-B",
      "facultyId": "F001",
      "facultyName": "Demo Teacher",
      "name": "abhinav",
      "section": "B",
      "status": "present",
      "time": "16:48:00",
      "timestamp": "2026-02-10T06:45:11.331000",
      "type": "dummy"
    },
    {
      "_id": "698ad3f9564599db88359814",
      "date": "2026-02-01",
      "subject": "Java Programming",
      "rollNo": "24EG107B01",
      "className": "Section-B",
      "facultyId": "F001",
      "facultyName": "Demo Teacher",
      "name": "abhinav",
      "section": "B",
      "status": "present",
      "time": "14:29:00",
      "timestamp": "2026-02-10T06:45:02.812000",
      "type": "dummy"
    },
    {
      "_id": "698ad3fd564599db88359815",
      "rollNo": "24EG107B01",
      "date": "2026-01-29",
      "subject": "Java Programming",
      "className": "Section-B",
      "facultyId": "F001",
      "facultyName": "Demo Teacher",
      "name": "abhinav",
      "section": "B",
      "status": "present",
      "time": "11:13:00",
      "timestamp": "2026-02-10T06:45:12.591000",
      "type": "dummy"
    },
    {
      "_id": "698ad3fe564599db88359816",
      "rollNo": "24EG107B01",
      "subject": "Java Programming",
      "date": "2026-01-19",
      "className": "Section-B",
      "facultyId": "F001",
      "facultyName": "Demo Teacher",
      "name": "abhinav",
      "section": "B",
      "status": "present",
      "time": "13:06:00",
      "timestamp": "2026-02-10T06:45:15.086000",
      "type": "dummy"
    },
    {
      "_id": "698ad3fe564599db88359817",
      "rollNo": "24EG107B01",
      "date": "2026-02-10",
      "subject": "Java Programming",
      "className": "Section-B",
      "facultyId": "F001",
      "facultyName": "Demo Teacher",
      "name": "abhinav",
      "section": "B",
      "status": "absent",
      "time": "12:20:00",
      "timestamp": "2026-02-10T06:45:15.767000",
      "type": "dummy"
    },
    {
      "_id": "698ad3ff564599db88359818",
      "rollNo": "24EG107B01",
      "date": "2026-02-03",
      "subject": "Java Programming",
      "className": "Section-B",
      "facultyId": "F001",
      "facultyName": "Demo Teacher",
      "name": "abhinav",
      "section": "B",
      "status": "absent",
      "time": "11:41:00",
      "timestamp": "2026-02-10T06:45:16.259000",
      "type": "dummy"
    },
    {
      "_id": "698ad3ff564599db88359819",
      "rollNo": "24EG107B01",
      "subject": "Java Programming",
      "date": "2026-01-22",
      "className": "Section-B",
      "facultyId": "F001",
      "facultyName": "Demo Teacher",
      "name": "abhinav",
      "section": "B",
      "status": "present",
      "time": "15:11:00",
      "timestamp": "2026-02-10T06:45:17.074000",
      "type": "dummy"
    },
    {
      "_id": "698ad400564599db8835981a",
      "date": "2026-01-31",
      "rollNo": "24EG107B01",
      "subject": "Java Programming",
      "className": "Section-B",
      "facultyId": "F001",
      "facultyName": "Demo Teacher",
      "name": "abhinav",
      "section": "B",
      "status": "present",
      "time": "15:15:00",
      "timestamp": "2026-02-10T06:45:17.560000",
      "type": "dummy"
    },
    {
      "_id": "698ad402564599db8835981b",
      "rollNo": "24EG107B01",
      "date": "2026-02-06",
      "subject": "Java Programming",
      "className": "Section-B",
      "facultyId": "F001",
      "facultyName": "Demo Teacher",
      "name": "abhinav",
      "section": "B",
      "status": "present",
      "time": "16:02:00",
      "timestamp": "2026-02-10T06:45:18.669000",
      "type": "dummy"
    },
    {
      "_id": "698ad404564599db8835981c",
      "date": "2026-01-20",
      "rollNo": "24EG107B01",
      "subject": "Java Programming",
      "className": "Section-B",
      "facultyId": "F001",
      "facultyName": "Demo Teacher",
      "name": "abhinav",
      "section": "B",
      "status": "present",
      "time": "15:23:00",
      "timestamp": "2026-02-10T06:45:20.674000",
      "type": "dummy"
    },
    {
      "_id": "698ad405564599db8835981d",
      "rollNo": "24EG107B01",
      "subject": "Java Programming",
      "date": "2026-02-04",
      "className": "Section-B",
      "facultyId": "F001",
      "facultyName": "Demo Teacher",
      "name": "abhinav",
      "section": "B",
      "status": "absent",
      "time": "13:16:00",
      "timestamp": "2026-02-10T06:45:22.487000",
      "type": "dummy"
    },
    {
      "_id": "698ad405564599db8835981e",
      "date": "2026-01-21",
      "subject": "Java Programming",
      "rollNo": "24EG107B01",
      "className": "Section-B",
      "facultyId": "F001",
      "facultyName": "Demo Teacher",
      "name": "abhinav",
      "section": "B",
      "status": "present",
      "time": "15:35:00",
      "timestamp": "2026-02-10T06:45:23.012000",
      "type": "dummy"
    },
    {
      "_id": "698ad408564599db8835981f",
      "rollNo": "24EG107B01",
      "subject": "EML Lab",
      "date": "2026-01-21",
      "className": "Section-B",
      "facultyId": "F001",
      "facultyName": "Demo Teacher",
      "name": "abhinav",
      "section": "B",
      "status": "present",
      "time": "15:59:00",
      "timestamp": "2026-02-10T06:45:31.858000",
      "type": "dummy"
    },
    {
      "_id": "698ad409564599db88359820",
      "rollNo": "24EG107B01",
      "date": "2026-02-01",
      "subject": "EML Lab",
      "className": "Section-B",
      "facultyId": "F001",
      "facultyName": "Demo Teacher",
      "name": "abhinav",
      "section": "B",
      "status": "present",
      "time": "15:01:00",
      "timestamp": "2026-02-10T06:45:26.159000",
      "type": "dummy"
    },
    {
      "_id": "698ad40a564599db88359821",
      "date": "2026-01-26",
      "rollNo": "24EG107B01",
      "subject": "EML Lab",
      "className": "Section-B",
      "facultyId": "F001",
      "facultyName": "Demo Teacher",
      "name": "abhinav",
      "section": "B",
      "status": "absent",
      "time": "11:25:00",
      "timestamp": "2026-02-10T06:45:27.607000",
      "type": "dummy"
    },
    {
      "_id": "698ad40c564599db88359822",
      "date": "2026-01-16",
      "subject": "EML Lab",
      "rollNo": "24EG107B01",
      "className": "Section-B",
      "facultyId": "F001",
      "facultyName": "Demo Teacher",
      "name": "abhinav",
      "section": "B",
      "status": "present",
      "time": "15:50:00",
      "timestamp": "2026-02-10T06:45:28.242000",
      "type": "dummy"
    },
    {
      "_id": "698ad40d564599db88359823",
      "date": "2026-01-30",
      "rollNo": "24EG107B01",
      "subject": "EML Lab",
      "className": "Section-B",
      "facultyId": "F001",
      "facultyName": "Demo Teacher",
      "name": "abhinav",
      "section": "B",
      "status": "present",
      "time": "14:30:00",
      "timestamp": "2026-02-10T06:45:30.336000",
      "type": "dummy"
    },
    {
      "_id": "698ad40d564599db88359824",
      "rollNo": "24EG107B01",
      "date": "2026-02-09",
      "subject": "EML Lab",
      "className": "Section-B",
      "facultyId": "F001",
      "facultyName": "Demo Teacher",
      "name": "abhinav",
      "section": "B",
      "status": "present",
      "time": "14:57:00",
      "timestamp": "2026-02-10T06:45:30.753000",
      "type": "dummy"
    }
  ]
}